LingmoPyUI/LingmoAccentColor.py
LingmoPyUI/LingmoApp.py
LingmoPyUI/LingmoColor.py
LingmoPyUI/LingmoDefines.py
LingmoPyUI/LingmoFrameless.py
LingmoPyUI/LingmoIconDef.py
LingmoPyUI/LingmoTextStyle.py
LingmoPyUI/LingmoTheme.py
LingmoPyUI/LingmoTools.py
LingmoPyUI/LingmoUnits.py
LingmoPyUI/__init__.py
LingmoPyUI/GraphicalEffects/__init__.py
lingmopyui-1.0.16.data/data/Lib/site-packages/LingmoPyUI/Font/FluentIcons.ttf
lingmopyui-1.0.16.data/data/Lib/site-packages/LingmoPyUI/Image/btn_close_hovered.png
lingmopyui-1.0.16.data/data/Lib/site-packages/LingmoPyUI/Image/btn_close_normal.png
lingmopyui-1.0.16.data/data/Lib/site-packages/LingmoPyUI/Image/btn_close_pushed.png
lingmopyui-1.0.16.data/data/Lib/site-packages/LingmoPyUI/Image/btn_max_hovered.png
lingmopyui-1.0.16.data/data/Lib/site-packages/LingmoPyUI/Image/btn_max_normal.png
lingmopyui-1.0.16.data/data/Lib/site-packages/LingmoPyUI/Image/btn_max_pushed.png
lingmopyui-1.0.16.data/data/Lib/site-packages/LingmoPyUI/Image/btn_min_hovered.png
lingmopyui-1.0.16.data/data/Lib/site-packages/LingmoPyUI/Image/btn_min_normal.png
lingmopyui-1.0.16.data/data/Lib/site-packages/LingmoPyUI/Image/btn_min_pushed.png
lingmopyui-1.0.16.data/data/Lib/site-packages/LingmoPyUI/Image/icon.png
lingmopyui-1.0.16.data/data/Lib/site-packages/LingmoPyUI/Image/noise.png
lingmopyui-1.0.16.dist-info/LICENSE
lingmopyui-1.0.16.dist-info/METADATA
lingmopyui-1.0.16.dist-info/WHEEL
lingmopyui-1.0.16.dist-info/top_level.txt
lingmopyui-1.0.16.dist-info/RECORD
