Metadata-Version: 2.2
Name: lingmopyui
Version: 1.0.16
Summary: A Lingmo GUI Library based on PySide6.QtWidgets
Home-page: https://github.com/LingmoOS/LingmoPyUI
Author: Admibrill
Author-email: admibrill@outlook.com
Classifier: Programming Language :: Python :: 3
Classifier: Operating System :: OS Independent
Requires-Python: >=3.6
License-File: LICENSE
Dynamic: author
Dynamic: author-email
Dynamic: classifier
Dynamic: description
Dynamic: description-content-type
Dynamic: home-page
Dynamic: requires-python
Dynamic: summary
